cdk_simple_serverless/__init__.py
cdk_simple_serverless/py.typed
cdk_simple_serverless/_jsii/__init__.py
cdk_simple_serverless/_jsii/cdk-simple-serverless@2.0.273.jsii.tgz
cdk_simple_serverless-2.0.273.dist-info/LICENSE
cdk_simple_serverless-2.0.273.dist-info/METADATA
cdk_simple_serverless-2.0.273.dist-info/WHEEL
cdk_simple_serverless-2.0.273.dist-info/top_level.txt
cdk_simple_serverless-2.0.273.dist-info/RECORD
